{
  "kind": "singleType",
  "collectionName": "payment_modes",
  "info": {
    "singularName": "payment-mode",
    "pluralName": "payment-modes",
    "displayName": "payment-modes"
  },
  "options": {
    "draftAndPublish": true
  },
  "pluginOptions": {},
  "attributes": {
    "content": {
      "type": "customField",
      "customField": "plugin::ckeditor5.CKEditor",
      "options": {
        "preset": "defaultHtml"
      },
      "required": true
    },
    "page": {
      "type": "string",
      "private": true,
      "default": "Contact",
      "required": true
    }
  }
}
